hammadcore/__init__.py
hammadcore/core.py
hammadcore/modules/__init__.py
hammadcore/modules/loaders.py
hammadcore/modules/text.py
hammadcore-0.0.1.dist-info/METADATA
hammadcore-0.0.1.dist-info/WHEEL
hammadcore-0.0.1.dist-info/top_level.txt
hammadcore-0.0.1.dist-info/RECORD
